soccer_summarizator/__init__.py
soccer_summarizator/model_builder.py
soccer_summarizator/soccer_summarizator.py
soccer_summarizator/checkpoints/resnet.pth
soccer_summarizator/checkpoints/squeezenet.pth
soccer_summarizator-0.1.2.dist-info/METADATA
soccer_summarizator-0.1.2.dist-info/WHEEL
soccer_summarizator-0.1.2.dist-info/top_level.txt
soccer_summarizator-0.1.2.dist-info/RECORD
